README.rst
setup.cfg
setup.py
XenonMKV.egg-info/PKG-INFO
XenonMKV.egg-info/SOURCES.txt
XenonMKV.egg-info/dependency_links.txt
XenonMKV.egg-info/entry_points.txt
XenonMKV.egg-info/top_level.txt
XenonMKV.egg-info/zip-safe
xenonmkv/__init__.py
xenonmkv/batch.py
xenonmkv/tests.py
xenonmkv/xenonmkv.py
xenonmkv/utils/__init__.py
xenonmkv/utils/encoder.py
xenonmkv/utils/file_utils.py
xenonmkv/utils/mkv_info_parser.py
xenonmkv/utils/mkvfile.py
xenonmkv/utils/mp4box.py
xenonmkv/utils/process_handler.py
xenonmkv/utils/reference_frame.py
xenonmkv/utils/support_tools.py
xenonmkv/utils/text.py
xenonmkv/utils/track.py