Metadata-Version: 1.1
Name: XenonMKV
Version: 0.4.3
Summary: XenonMKV is a video container conversion tool that takes MKV files and outputs them as MP4 files.
Home-page: https://github.com/barisariburnu/xenonmkv
Author: barisariburnu
Author-email: barisariburnu@gmail.com
License: UNKNOWN
Download-URL: https://github.com/barisariburnu/xenonmkv/tarball/0.4.3
Keywords: MKV Container MP4 XenonMKV
Platform: UNKNOWN
Classifier: Development Status :: 3 - Alpha
Classifier: Intended Audience :: Developers
Classifier: License :: OSI Approved :: GNU General Public License (GPL)
Classifier: Operating System :: OS Independent
Classifier: Programming Language :: Python
Classifier: Programming Language :: Python :: 2.7
Classifier: Topic :: Multimedia :: Sound/Audio
Classifier: Topic :: Utilities
